jolly/__init__.py
jolly/config.py
jolly/definitions.py
jolly/env.py
jolly/exp.py
jolly/logger.py
jolly/models.py
jolly/db/__init__.py
jolly/db/dynamo_db.py
jolly/db/dynamo_table.py
jolly/db/jolly_instances_table.py
jolly/db/jolly_resources_table.py
jolly/db/table.py
jolly/services/__init__.py
jolly/services/abstract_jolly_service.py
jolly/services/jolly_instance_services/__init__.py
jolly/services/jolly_instance_services/select_jolly_instance_service.py
jolly/services/jolly_instance_services/update_jolly_instance_load_service.py
jolly/services/jolly_resource_services/__init__.py
jolly/services/jolly_resource_services/create_jolly_resource_service.py
jolly-0.0.1.dist-info/METADATA
jolly-0.0.1.dist-info/WHEEL
jolly-0.0.1.dist-info/top_level.txt
jolly-0.0.1.dist-info/RECORD
