Metadata-Version: 2.1
Name: jolly
Version: 0.0.1
Summary: Jolly Python Client
Home-page: https://github.com/whittlbc/jolly-py
Author: Ben Whittle
Author-email: benwhittle31@gmail.com
License: MIT
Platform: UNKNOWN
Requires-Dist: boto3 (==1.17.22)
